MANIFEST.in
README.md
setup.py
netbox_reports_plugin/__init__.py
netbox_reports_plugin/filters.py
netbox_reports_plugin/forms.py
netbox_reports_plugin/models.py
netbox_reports_plugin/navigation.py
netbox_reports_plugin/tables.py
netbox_reports_plugin/urls.py
netbox_reports_plugin/views.py
netbox_reports_plugin.egg-info/PKG-INFO
netbox_reports_plugin.egg-info/SOURCES.txt
netbox_reports_plugin.egg-info/dependency_links.txt
netbox_reports_plugin.egg-info/requires.txt
netbox_reports_plugin.egg-info/top_level.txt
netbox_reports_plugin/migrations/0001_initial.py
netbox_reports_plugin/migrations/0002_auto_20221208_1531.py
netbox_reports_plugin/migrations/0003_alter_equipmentdata_options.py
netbox_reports_plugin/migrations/0004_auto_20221221_0844.py
netbox_reports_plugin/migrations/__init__.py
netbox_reports_plugin/templates/netbox_reports_plugin/reports_device_list.html