Metadata-Version: 2.1
Name: netbox-reports-plugin
Version: 0.12
Summary: netbox_reports_plugin
Home-page: UNKNOWN
Author: Ilya Gulin
License: Apache 2.0
Platform: UNKNOWN
